hydrolib/_PlatFormGetter.py
hydrolib/__about__.py
hydrolib/__error_hook.py
hydrolib/__init__.py
hydrolib/_qstruct.old.py
hydrolib/auth.py
hydrolib/auto_struct.py
hydrolib/const.py
hydrolib/coro_plus.py
hydrolib/database.py
hydrolib/decorators.py
hydrolib/encryio.py
hydrolib/env_plus.py
hydrolib/example.py
hydrolib/file.py
hydrolib/hash.py
hydrolib/hytime.py
hydrolib/hywinreg.py
hydrolib/import_plus.py
hydrolib/io_addons.py
hydrolib/json_file.py
hydrolib/logging_methods.py
hydrolib/network.py
hydrolib/ospipe.py
hydrolib/output_methods.py
hydrolib/path.py
hydrolib/process.py
hydrolib/process_addons.py
hydrolib/quick_aiohttp.py
hydrolib/signal.py
hydrolib/socket.py
hydrolib/socket_plus.py
hydrolib/struct_plus.py
hydrolib/sys_plus.py
hydrolib/threading_methods.py
hydrolib/abc/__init__.py
hydrolib/boardcast_room/__init__.py
hydrolib/boardcast_room/_packages.py
hydrolib/boardcast_room/errors.py
hydrolib/boardcast_room/socket.py
hydrolib/codedoc/Struct.py
hydrolib/codedoc/__init__.py
hydrolib/data_structures/BplusTree.py
hydrolib/data_structures/Graph.py
hydrolib/data_structures/HuffmanTree.py
hydrolib/data_structures/Tree.py
hydrolib/data_structures/__init__.py
hydrolib/data_structures/ThreadSafeCollections/__init__.py
hydrolib/data_structures/ThreadSafeCollections/any_like.py
hydrolib/data_structures/ThreadSafeCollections/dict_like.py
hydrolib/data_structures/ThreadSafeCollections/list_like.py
hydrolib/encrypt/__init__.py
hydrolib/encrypt/aes.py
hydrolib/encrypt/both.py
hydrolib/encrypt/func.py
hydrolib/encrypt/rsa.py
hydrolib/hyconfig/__init__.py
hydrolib/hyconfig/Interpreter/Interpreter.py
hydrolib/hyconfig/Interpreter/Lexer.py
hydrolib/hyconfig/Interpreter/Parser.py
hydrolib/hyconfig/Interpreter/__init__.py
hydrolib/hyconfig/Interpreter/_funs.py
hydrolib/hydownloader/TaskManager.py
hydrolib/hydownloader/UnitConversion.py
hydrolib/hydownloader/_Base.py
hydrolib/hydownloader/__init__.py
hydrolib/hystruct/__init__.py
hydrolib/hystruct/Serializers/Abc.py
hydrogenlib-1.1.33.dist-info/METADATA
hydrogenlib-1.1.33.dist-info/WHEEL
hydrogenlib-1.1.33.dist-info/licenses/License.md
hydrogenlib-1.1.33.dist-info/licenses/License_CN.md
hydrogenlib-1.1.33.dist-info/RECORD
