Metadata-Version: 2.3
Name: HydrogenLib
Version: 1.1.33
Project-URL: Documentation, https://github.com/SongzqInChina/HydrogenLib#readme
Project-URL: Issues, https://github.com/SongzqInChina/HydrogenLib/issues
Project-URL: Source, https://github.com/SongzqInChina/HydrogenLib
Author-email: SongzqInChina <idesong6@qq.com>
Classifier: Development Status :: 4 - Beta
Classifier: Programming Language :: Python
Classifier: Programming Language :: Python :: 3.12
Classifier: Programming Language :: Python :: Implementation :: CPython
Classifier: Programming Language :: Python :: Implementation :: PyPy
Requires-Python: >=3.7.0
Requires-Dist: jsonpickle>=3.3.0
Requires-Dist: ping3>=4.0.0
Requires-Dist: psutil>=6.0.0
Requires-Dist: pyaes>=1.6.0
Requires-Dist: pywin32>=306
Requires-Dist: rich>=13.6.0
Requires-Dist: rsa>=4.9
